{"node":{"7f0d3b7fb22dda6666b9a8b4c7bb66f4ed47dd11e1":{"workers":{"app/[locale]/[slug]/page":{"moduleId":"75655","async":false},"app/[locale]/blog/page":{"moduleId":"75655","async":false},"app/[locale]/team/page":{"moduleId":"75655","async":false}},"layer":{"app/[locale]/[slug]/page":"action-browser","app/[locale]/blog/page":"action-browser","app/[locale]/team/page":"action-browser"}},"7f97fceff669ae4e354c0cd246addcec3970f80af2":{"workers":{"app/[locale]/[slug]/page":{"moduleId":"75655","async":false},"app/[locale]/blog/page":{"moduleId":"75655","async":false},"app/[locale]/team/page":{"moduleId":"75655","async":false}},"layer":{"app/[locale]/[slug]/page":"action-browser","app/[locale]/blog/page":"action-browser","app/[locale]/team/page":"action-browser"}},"7fdc6ba58d240c7289f47a19b379cfebf0848a6201":{"workers":{"app/[locale]/[slug]/page":{"moduleId":"75655","async":false},"app/[locale]/blog/page":{"moduleId":"75655","async":false},"app/[locale]/team/page":{"moduleId":"75655","async":false}},"layer":{"app/[locale]/[slug]/page":"action-browser","app/[locale]/blog/page":"action-browser","app/[locale]/team/page":"action-browser"}}},"edge":{},"encryptionKey":"hh1IAryrOia8GoBkyikmeFTJmjjZYC9fGv+/B3+WP5o="}